LICENSE
README.md
pyproject.toml
setup.py
tatarubot2/__init__.py
tatarubot2.egg-info/PKG-INFO
tatarubot2.egg-info/SOURCES.txt
tatarubot2.egg-info/dependency_links.txt
tatarubot2.egg-info/requires.txt
tatarubot2.egg-info/top_level.txt
tatarubot2/plugins/__init__.py
tatarubot2/plugins/auto_response.py
tatarubot2/plugins/bot_help.py
tatarubot2/plugins/chat_ai.py
tatarubot2/plugins/ff_weibo.py
tatarubot2/plugins/house.py
tatarubot2/plugins/item.py
tatarubot2/plugins/item_new.py
tatarubot2/plugins/logs_dps.py
tatarubot2/plugins/lottery.py
tatarubot2/plugins/market.py
tatarubot2/plugins/market_new.py
tatarubot2/plugins/nuannuan.py
tatarubot2/plugins/precious.py
tatarubot2/plugins/weather.py
tatarubot2/tools/__init__.py
tatarubot2/tools/download_boss.py
tatarubot2/tools/download_item2id.py
tatarubot2/tools/normal_data.py