Metadata-Version: 2.1
Name: tatarubot2
Version: 0.1.0
Summary: FF14 bot Tataru
Author: aaron-li
Author-email: 
License-File: LICENSE
